tests/__init__.py
tests/examples_generator.py
tests/models/__init__.py
torchvista/__init__.py
torchvista/overrides.py
torchvista/tracer.py
torchvista/assets/__init__.py
torchvista/assets/d3.min.js
torchvista/assets/jsoneditor-10.2.0.min.css
torchvista/assets/jsoneditor-10.2.0.min.js
torchvista/assets/viz-standalone.js
torchvista/templates/__init__.py
torchvista/templates/demo-graph.html
torchvista/templates/graph.html
torchvista-0.2.11.dist-info/licenses/LICENSE
torchvista-0.2.11.dist-info/licenses/NOTICE.txt
torchvista-0.2.11.dist-info/METADATA
torchvista-0.2.11.dist-info/WHEEL
torchvista-0.2.11.dist-info/top_level.txt
torchvista-0.2.11.dist-info/RECORD
