Metadata-Version: 2.4
Name: torchvista
Version: 0.2.11
Summary: Interactive PyTorch model visualizer for notebooks
Classifier: Development Status :: 3 - Alpha
Classifier: Natural Language :: English
Classifier: Programming Language :: Python :: 3
Requires-Python: >=3.8
License-File: LICENSE
License-File: NOTICE.txt
Requires-Dist: ipython>=7.0.0
Requires-Dist: numpy>=1.18.0
Dynamic: classifier
Dynamic: description
Dynamic: description-content-type
Dynamic: license-file
Dynamic: requires-dist
Dynamic: requires-python
Dynamic: summary
